odoo10_addon_web_widget_mermaid-10.0.8.4.0.99.dev2-py3.8-nspkg.pth
odoo/addons/web_widget_mermaid/README.rst
odoo/addons/web_widget_mermaid/__init__.py
odoo/addons/web_widget_mermaid/__manifest__.py
odoo/addons/web_widget_mermaid/demo/res_users_flowchart.xml
odoo/addons/web_widget_mermaid/readme/CONTRIBUTORS.rst
odoo/addons/web_widget_mermaid/readme/DESCRIPTION.rst
odoo/addons/web_widget_mermaid/readme/USAGE.rst
odoo/addons/web_widget_mermaid/static/description/flowchart_example.png
odoo/addons/web_widget_mermaid/static/description/icon.png
odoo/addons/web_widget_mermaid/static/description/index.html
odoo/addons/web_widget_mermaid/static/lib/mermaid/mermaid.js
odoo/addons/web_widget_mermaid/static/src/js/web_widget_mermaid.js
odoo/addons/web_widget_mermaid/static/src/less/web_widget_mermaid_default_theme.less
odoo/addons/web_widget_mermaid/static/src/xml/web_widget_mermaid.xml
odoo/addons/web_widget_mermaid/view/web_widget_mermaid_view.xml
odoo10_addon_web_widget_mermaid-10.0.8.4.0.99.dev2.dist-info/METADATA
odoo10_addon_web_widget_mermaid-10.0.8.4.0.99.dev2.dist-info/WHEEL
odoo10_addon_web_widget_mermaid-10.0.8.4.0.99.dev2.dist-info/namespace_packages.txt
odoo10_addon_web_widget_mermaid-10.0.8.4.0.99.dev2.dist-info/top_level.txt
odoo10_addon_web_widget_mermaid-10.0.8.4.0.99.dev2.dist-info/RECORD
